krunnerdbusutils/Action.py
krunnerdbusutils/Annotations.py
krunnerdbusutils/Match.py
krunnerdbusutils/__init__.py
krunnerdbusutils/py.typed
krunnerdbusutils-0.1.2.dist-info/METADATA
krunnerdbusutils-0.1.2.dist-info/WHEEL
krunnerdbusutils-0.1.2.dist-info/top_level.txt
krunnerdbusutils-0.1.2.dist-info/RECORD
