Metadata-Version: 2.1
Name: krunnerdbusutils
Version: 0.1.2
Summary: A utility library for interacting with the KRunner API via D-Bus
Home-page: https://github.com/alex1701c/krunnerdbusutils
Author: Alexander Lohnau
Author-email: alex1701c.dev@gmx.net
Requires-Python: >=3.10
Requires-Dist: dbus-python
